{"scope":{"breadcrumbs":[{"timestamp":1747683150.311,"category":"console","data":{"arguments":["Unsubscribing from direct frames for streamId 10"],"logger":"console"},"level":"info","message":"Unsubscribing from direct frames for streamId 10"},{"timestamp":1747683251.428,"category":"electron","message":"window.focus","type":"ui","data":{"id":2,"url":"https://discord.com/channels/902483466308956241/910997069379026964"}},{"timestamp":1747683251.428,"category":"electron","message":"app.browser-window-focus","type":"ui"},{"timestamp":1747683251.453,"category":"console","data":{"arguments":["Subscribing to direct frames for streamId 10"],"logger":"console"},"level":"info","message":"Subscribing to direct frames for streamId 10"},{"timestamp":1747683252.309,"category":"ui.click","message":"g > g > g > g > path"},{"timestamp":1747683252.563,"category":"electron","message":"window.blur","type":"ui","data":{"id":2,"url":"https://discord.com/channels/902483466308956241/910997069379026964"}},{"timestamp":1747683252.563,"category":"electron","message":"app.browser-window-blur","type":"ui"},{"timestamp":1747683252.605,"category":"console","data":{"arguments":["Unsubscribing from direct frames for streamId 10"],"logger":"console"},"level":"info","message":"Unsubscribing from direct frames for streamId 10"},{"timestamp":1747683308.788,"category":"electron","message":"window.focus","type":"ui","data":{"id":2,"url":"https://discord.com/channels/902483466308956241/910997069379026964"}},{"timestamp":1747683308.788,"category":"electron","message":"app.browser-window-focus","type":"ui"},{"timestamp":1747683308.811,"category":"console","data":{"arguments":["Subscribing to direct frames for streamId 10"],"logger":"console"},"level":"info","message":"Subscribing to direct frames for streamId 10"},{"timestamp":1747683309.889,"category":"ui.click","message":"g > g > g > g > path"},{"timestamp":1747683310.083,"category":"electron","message":"window.blur","type":"ui","data":{"id":2,"url":"https://discord.com/channels/902483466308956241/910997069379026964"}},{"timestamp":1747683310.083,"category":"electron","message":"app.browser-window-blur","type":"ui"},{"timestamp":1747683310.126,"category":"console","data":{"arguments":["Unsubscribing from direct frames for streamId 10"],"logger":"console"},"level":"info","message":"Unsubscribing from direct frames for streamId 10"},{"timestamp":1747683422.108,"category":"electron","message":"window.focus","type":"ui","data":{"id":2,"url":"https://discord.com/channels/902483466308956241/910997069379026964"}},{"timestamp":1747683422.108,"category":"electron","message":"app.browser-window-focus","type":"ui"},{"timestamp":1747683422.134,"category":"console","data":{"arguments":["Subscribing to direct frames for streamId 10"],"logger":"console"},"level":"info","message":"Subscribing to direct frames for streamId 10"},{"timestamp":1747683423.137,"category":"ui.click","message":"button.centerButton_f1ceac.colorable_f1ceac.primaryDark_f1ceac.attachedButton_f1ceac.button__201d5.lookBlank__201d5.colorBrand__201d5[aria-label=\"Mute\"][type=\"button\"]"},{"timestamp":1747683423.41,"category":"electron","message":"window.blur","type":"ui","data":{"id":2,"url":"https://discord.com/channels/902483466308956241/910997069379026964"}},{"timestamp":1747683423.41,"category":"electron","message":"app.browser-window-blur","type":"ui"},{"timestamp":1747683423.443,"category":"console","data":{"arguments":["Unsubscribing from direct frames for streamId 10"],"logger":"console"},"level":"info","message":"Unsubscribing from direct frames for streamId 10"},{"timestamp":1747683484.873,"category":"electron","message":"window.focus","type":"ui","data":{"id":2,"url":"https://discord.com/channels/902483466308956241/910997069379026964"}},{"timestamp":1747683484.874,"category":"electron","message":"app.browser-window-focus","type":"ui"},{"timestamp":1747683484.899,"category":"console","data":{"arguments":["Subscribing to direct frames for streamId 10"],"logger":"console"},"level":"info","message":"Subscribing to direct frames for streamId 10"},{"timestamp":1747683485.727,"category":"ui.click","message":"svg"},{"timestamp":1747683485.91,"category":"electron","message":"window.blur","type":"ui","data":{"id":2,"url":"https://discord.com/channels/902483466308956241/910997069379026964"}},{"timestamp":1747683485.91,"category":"electron","message":"app.browser-window-blur","type":"ui"},{"timestamp":1747683485.963,"category":"console","data":{"arguments":["Unsubscribing from direct frames for streamId 10"],"logger":"console"},"level":"info","message":"Unsubscribing from direct frames for streamId 10"},{"timestamp":1747683565.809,"category":"electron","message":"window.focus","type":"ui","data":{"id":2,"url":"https://discord.com/channels/902483466308956241/910997069379026964"}},{"timestamp":1747683565.809,"category":"electron","message":"app.browser-window-focus","type":"ui"},{"timestamp":1747683565.829,"category":"console","data":{"arguments":["Subscribing to direct frames for streamId 10"],"logger":"console"},"level":"info","message":"Subscribing to direct frames for streamId 10"},{"timestamp":1747683566.776,"category":"ui.click","message":"svg"},{"timestamp":1747683566.947,"category":"electron","message":"window.blur","type":"ui","data":{"id":2,"url":"https://discord.com/channels/902483466308956241/910997069379026964"}},{"timestamp":1747683566.947,"category":"electron","message":"app.browser-window-blur","type":"ui"},{"timestamp":1747683566.984,"category":"console","data":{"arguments":["Unsubscribing from direct frames for streamId 10"],"logger":"console"},"level":"info","message":"Unsubscribing from direct frames for streamId 10"},{"timestamp":1747683620.367,"category":"http","data":{"status_code":200,"url":"https://api.github.com/repos/Vendicated/Vencord/releases/latest","http.method":"GET"},"type":"http"},{"timestamp":1747683620.46,"category":"http","data":{"status_code":200,"url":"https://api.github.com/repos/Vendicated/Vencord/compare/8473b59...HEAD","http.method":"GET"},"type":"http"},{"timestamp":1747683620.524,"category":"http","data":{"status_code":200,"url":"https://api.github.com/repos/Vendicated/Vencord/releases/latest","http.method":"GET"},"type":"http"},{"timestamp":1747683620.633,"category":"http","data":{"status_code":302,"url":"https://github.com/Vendicated/Vencord/releases/download/devbuild/patcher.js.LEGAL.txt","http.method":"GET"},"type":"http"},{"timestamp":1747683620.635,"category":"http","data":{"status_code":302,"url":"https://github.com/Vendicated/Vencord/releases/download/devbuild/patcher.js","http.method":"GET"},"type":"http"},{"timestamp":1747683620.636,"category":"http","data":{"status_code":302,"url":"https://github.com/Vendicated/Vencord/releases/download/devbuild/patcher.js.map","http.method":"GET"},"type":"http"},{"timestamp":1747683620.641,"category":"http","data":{"status_code":302,"url":"https://github.com/Vendicated/Vencord/releases/download/devbuild/renderer.css","http.method":"GET"},"type":"http"},{"timestamp":1747683620.642,"category":"http","data":{"status_code":302,"url":"https://github.com/Vendicated/Vencord/releases/download/devbuild/preload.js","http.method":"GET"},"type":"http"},{"timestamp":1747683620.644,"category":"http","data":{"status_code":302,"url":"https://github.com/Vendicated/Vencord/releases/download/devbuild/renderer.css.map","http.method":"GET"},"type":"http"},{"timestamp":1747683620.647,"category":"http","data":{"status_code":302,"url":"https://github.com/Vendicated/Vencord/releases/download/devbuild/renderer.js.LEGAL.txt","http.method":"GET"},"type":"http"},{"timestamp":1747683620.649,"category":"http","data":{"status_code":302,"url":"https://github.com/Vendicated/Vencord/releases/download/devbuild/renderer.js","http.method":"GET"},"type":"http"},{"timestamp":1747683620.653,"category":"http","data":{"status_code":302,"url":"https://github.com/Vendicated/Vencord/releases/download/devbuild/renderer.js.map","http.method":"GET"},"type":"http"},{"timestamp":1747683620.657,"category":"http","data":{"status_code":302,"url":"https://github.com/Vendicated/Vencord/releases/download/devbuild/patcher.js","http.method":"GET"},"type":"http"},{"timestamp":1747683620.658,"category":"http","data":{"status_code":302,"url":"https://github.com/Vendicated/Vencord/releases/download/devbuild/patcher.js.LEGAL.txt","http.method":"GET"},"type":"http"},{"timestamp":1747683620.659,"category":"http","data":{"status_code":302,"url":"https://github.com/Vendicated/Vencord/releases/download/devbuild/renderer.css","http.method":"GET"},"type":"http"},{"timestamp":1747683620.662,"category":"http","data":{"status_code":302,"url":"https://github.com/Vendicated/Vencord/releases/download/devbuild/renderer.js.map","http.method":"GET"},"type":"http"},{"timestamp":1747683620.671,"category":"http","data":{"status_code":302,"url":"https://github.com/Vendicated/Vencord/releases/download/devbuild/renderer.js.LEGAL.txt","http.method":"GET"},"type":"http"},{"timestamp":1747683620.74,"category":"http","data":{"status_code":302,"url":"https://github.com/Vendicated/Vencord/releases/download/devbuild/preload.js","http.method":"GET"},"type":"http"},{"timestamp":1747683620.783,"category":"http","data":{"status_code":302,"url":"https://github.com/Vendicated/Vencord/releases/download/devbuild/preload.js.map","http.method":"GET"},"type":"http"},{"timestamp":1747683620.788,"category":"http","data":{"status_code":302,"url":"https://github.com/Vendicated/Vencord/releases/download/devbuild/renderer.js","http.method":"GET"},"type":"http"},{"timestamp":1747683620.829,"category":"http","data":{"status_code":302,"url":"https://github.com/Vendicated/Vencord/releases/download/devbuild/preload.js.map","http.method":"GET"},"type":"http"},{"timestamp":1747683620.838,"category":"http","data":{"status_code":302,"url":"https://github.com/Vendicated/Vencord/releases/download/devbuild/patcher.js.map","http.method":"GET"},"type":"http"},{"timestamp":1747683620.863,"category":"http","data":{"status_code":302,"url":"https://github.com/Vendicated/Vencord/releases/download/devbuild/renderer.css.map","http.method":"GET"},"type":"http"},{"timestamp":1747683620.971,"category":"http","data":{"status_code":200,"url":"https://objects.githubusercontent.com/github-production-release-asset-2e65be/528464304/78e66dcf-a72a-4f21-b50a-48e0c3788e13","http.method":"GET","http.query":"X-Amz-Algorithm=AWS4-HMAC-SHA256&X-Amz-Credential=releaseassetproduction%2F20250519%2Fus-east-1%2Fs3%2Faws4_request&X-Amz-Date=20250519T193837Z&X-Amz-Expires=300&X-Amz-Signature=ae47b5f4450e93ca537cf49fee3ee8cfc3647f6dac098e5e01814db5dbbf1d69&X-Amz-SignedHeaders=host&response-content-disposition=attachment%3B%20filename%3Dpatcher.js.map&response-content-type=application%2Foctet-stream"},"type":"http"},{"timestamp":1747683621.026,"category":"http","data":{"status_code":200,"url":"https://objects.githubusercontent.com/github-production-release-asset-2e65be/528464304/26a53e62-141b-4de6-b4e9-44a9e40ff360","http.method":"GET","http.query":"X-Amz-Algorithm=AWS4-HMAC-SHA256&X-Amz-Credential=releaseassetproduction%2F20250519%2Fus-east-1%2Fs3%2Faws4_request&X-Amz-Date=20250519T193837Z&X-Amz-Expires=300&X-Amz-Signature=0e46474a6d638de3205666352a238c99df3287d569e00d5e25eba032ee1eda74&X-Amz-SignedHeaders=host&response-content-disposition=attachment%3B%20filename%3Dpatcher.js.LEGAL.txt&response-content-type=application%2Foctet-stream"},"type":"http"},{"timestamp":1747683621.045,"category":"http","data":{"status_code":200,"url":"https://objects.githubusercontent.com/github-production-release-asset-2e65be/528464304/8c15ee34-4849-4cbc-9d6f-177e64804c97","http.method":"GET","http.query":"X-Amz-Algorithm=AWS4-HMAC-SHA256&X-Amz-Credential=releaseassetproduction%2F20250519%2Fus-east-1%2Fs3%2Faws4_request&X-Amz-Date=20250519T193837Z&X-Amz-Expires=300&X-Amz-Signature=ac17b37b353a28ea1711c2fd831f8ba1ab29898eb143bcce9999cae285ca2387&X-Amz-SignedHeaders=host&response-content-disposition=attachment%3B%20filename%3Drenderer.js.map&response-content-type=application%2Foctet-stream"},"type":"http"},{"timestamp":1747683621.05,"category":"http","data":{"status_code":200,"url":"https://objects.githubusercontent.com/github-production-release-asset-2e65be/528464304/f7305a1b-34ea-424f-a308-b06e2ffa7d4d","http.method":"GET","http.query":"X-Amz-Algorithm=AWS4-HMAC-SHA256&X-Amz-Credential=releaseassetproduction%2F20250519%2Fus-east-1%2Fs3%2Faws4_request&X-Amz-Date=20250519T193837Z&X-Amz-Expires=300&X-Amz-Signature=f864efdaa4746ae637cf1c835ccb675777dfa53466da24ef548092415850b002&X-Amz-SignedHeaders=host&response-content-disposition=attachment%3B%20filename%3Drenderer.css&response-content-type=application%2Foctet-stream"},"type":"http"},{"timestamp":1747683621.053,"category":"http","data":{"status_code":200,"url":"https://objects.githubusercontent.com/github-production-release-asset-2e65be/528464304/78e66dcf-a72a-4f21-b50a-48e0c3788e13","http.method":"GET","http.query":"X-Amz-Algorithm=AWS4-HMAC-SHA256&X-Amz-Credential=releaseassetproduction%2F20250519%2Fus-east-1%2Fs3%2Faws4_request&X-Amz-Date=20250519T193837Z&X-Amz-Expires=300&X-Amz-Signature=ae47b5f4450e93ca537cf49fee3ee8cfc3647f6dac098e5e01814db5dbbf1d69&X-Amz-SignedHeaders=host&response-content-disposition=attachment%3B%20filename%3Dpatcher.js.map&response-content-type=application%2Foctet-stream"},"type":"http"},{"timestamp":1747683621.06,"category":"http","data":{"status_code":200,"url":"https://objects.githubusercontent.com/github-production-release-asset-2e65be/528464304/88b964e1-8fc6-43f6-b9f1-c6f677942584","http.method":"GET","http.query":"X-Amz-Algorithm=AWS4-HMAC-SHA256&X-Amz-Credential=releaseassetproduction%2F20250519%2Fus-east-1%2Fs3%2Faws4_request&X-Amz-Date=20250519T193837Z&X-Amz-Expires=300&X-Amz-Signature=9f9413e6a84630d7d0a4060a233730259158338f524ac5249f026c5e9699788b&X-Amz-SignedHeaders=host&response-content-disposition=attachment%3B%20filename%3Drenderer.js&response-content-type=application%2Foctet-stream"},"type":"http"},{"timestamp":1747683621.064,"category":"http","data":{"status_code":200,"url":"https://objects.githubusercontent.com/github-production-release-asset-2e65be/528464304/af2c4f8a-ab4a-44ef-94c3-c66efb7739ad","http.method":"GET","http.query":"X-Amz-Algorithm=AWS4-HMAC-SHA256&X-Amz-Credential=releaseassetproduction%2F20250519%2Fus-east-1%2Fs3%2Faws4_request&X-Amz-Date=20250519T193837Z&X-Amz-Expires=300&X-Amz-Signature=736412b5ce7d93267464a11db9a006a21211d49fc8e54da189459da7bdbd9b1c&X-Amz-SignedHeaders=host&response-content-disposition=attachment%3B%20filename%3Drenderer.js.LEGAL.txt&response-content-type=application%2Foctet-stream"},"type":"http"},{"timestamp":1747683621.065,"category":"http","data":{"status_code":200,"url":"https://objects.githubusercontent.com/github-production-release-asset-2e65be/528464304/af2c4f8a-ab4a-44ef-94c3-c66efb7739ad","http.method":"GET","http.query":"X-Amz-Algorithm=AWS4-HMAC-SHA256&X-Amz-Credential=releaseassetproduction%2F20250519%2Fus-east-1%2Fs3%2Faws4_request&X-Amz-Date=20250519T193837Z&X-Amz-Expires=300&X-Amz-Signature=736412b5ce7d93267464a11db9a006a21211d49fc8e54da189459da7bdbd9b1c&X-Amz-SignedHeaders=host&response-content-disposition=attachment%3B%20filename%3Drenderer.js.LEGAL.txt&response-content-type=application%2Foctet-stream"},"type":"http"},{"timestamp":1747683621.094,"category":"http","data":{"status_code":200,"url":"https://objects.githubusercontent.com/github-production-release-asset-2e65be/528464304/26a53e62-141b-4de6-b4e9-44a9e40ff360","http.method":"GET","http.query":"X-Amz-Algorithm=AWS4-HMAC-SHA256&X-Amz-Credential=releaseassetproduction%2F20250519%2Fus-east-1%2Fs3%2Faws4_request&X-Amz-Date=20250519T193837Z&X-Amz-Expires=300&X-Amz-Signature=0e46474a6d638de3205666352a238c99df3287d569e00d5e25eba032ee1eda74&X-Amz-SignedHeaders=host&response-content-disposition=attachment%3B%20filename%3Dpatcher.js.LEGAL.txt&response-content-type=application%2Foctet-stream"},"type":"http"},{"timestamp":1747683621.094,"category":"http","data":{"status_code":200,"url":"https://objects.githubusercontent.com/github-production-release-asset-2e65be/528464304/f7305a1b-34ea-424f-a308-b06e2ffa7d4d","http.method":"GET","http.query":"X-Amz-Algorithm=AWS4-HMAC-SHA256&X-Amz-Credential=releaseassetproduction%2F20250519%2Fus-east-1%2Fs3%2Faws4_request&X-Amz-Date=20250519T193837Z&X-Amz-Expires=300&X-Amz-Signature=f864efdaa4746ae637cf1c835ccb675777dfa53466da24ef548092415850b002&X-Amz-SignedHeaders=host&response-content-disposition=attachment%3B%20filename%3Drenderer.css&response-content-type=application%2Foctet-stream"},"type":"http"},{"timestamp":1747683621.109,"category":"http","data":{"status_code":200,"url":"https://objects.githubusercontent.com/github-production-release-asset-2e65be/528464304/4a1329fe-5353-4f92-9a91-e57761e7322b","http.method":"GET","http.query":"X-Amz-Algorithm=AWS4-HMAC-SHA256&X-Amz-Credential=releaseassetproduction%2F20250519%2Fus-east-1%2Fs3%2Faws4_request&X-Amz-Date=20250519T193837Z&X-Amz-Expires=300&X-Amz-Signature=112fc2547721a34975435817a2a6ae8d93e755abebc8d9edf485d27cd7545d27&X-Amz-SignedHeaders=host&response-content-disposition=attachment%3B%20filename%3Drenderer.css.map&response-content-type=application%2Foctet-stream"},"type":"http"},{"timestamp":1747683621.119,"category":"http","data":{"status_code":200,"url":"https://objects.githubusercontent.com/github-production-release-asset-2e65be/528464304/678c9cbe-2c69-4744-b6de-bb609409e8f3","http.method":"GET","http.query":"X-Amz-Algorithm=AWS4-HMAC-SHA256&X-Amz-Credential=releaseassetproduction%2F20250519%2Fus-east-1%2Fs3%2Faws4_request&X-Amz-Date=20250519T193837Z&X-Amz-Expires=300&X-Amz-Signature=d189648abd6402de6b0ae27e48ba96b44e6cf950f141a77e9cfbd0f59c78ef4a&X-Amz-SignedHeaders=host&response-content-disposition=attachment%3B%20filename%3Dpatcher.js&response-content-type=application%2Foctet-stream"},"type":"http"},{"timestamp":1747683621.175,"category":"http","data":{"status_code":200,"url":"https://objects.githubusercontent.com/github-production-release-asset-2e65be/528464304/f498968d-4865-4b18-93a0-bc3493e19b07","http.method":"GET","http.query":"X-Amz-Algorithm=AWS4-HMAC-SHA256&X-Amz-Credential=releaseassetproduction%2F20250519%2Fus-east-1%2Fs3%2Faws4_request&X-Amz-Date=20250519T193931Z&X-Amz-Expires=300&X-Amz-Signature=5433335702d6ae5efaedfd17c2bcdd210cd4597ea307857d8f64e00087df94cb&X-Amz-SignedHeaders=host&response-content-disposition=attachment%3B%20filename%3Dpreload.js.map&response-content-type=application%2Foctet-stream"},"type":"http"},{"timestamp":1747683621.178,"category":"http","data":{"status_code":200,"url":"https://objects.githubusercontent.com/github-production-release-asset-2e65be/528464304/88b964e1-8fc6-43f6-b9f1-c6f677942584","http.method":"GET","http.query":"X-Amz-Algorithm=AWS4-HMAC-SHA256&X-Amz-Credential=releaseassetproduction%2F20250519%2Fus-east-1%2Fs3%2Faws4_request&X-Amz-Date=20250519T193837Z&X-Amz-Expires=300&X-Amz-Signature=9f9413e6a84630d7d0a4060a233730259158338f524ac5249f026c5e9699788b&X-Amz-SignedHeaders=host&response-content-disposition=attachment%3B%20filename%3Drenderer.js&response-content-type=application%2Foctet-stream"},"type":"http"},{"timestamp":1747683621.179,"category":"http","data":{"status_code":200,"url":"https://objects.githubusercontent.com/github-production-release-asset-2e65be/528464304/446b99c4-bfb6-4864-b2f2-833026b97699","http.method":"GET","http.query":"X-Amz-Algorithm=AWS4-HMAC-SHA256&X-Amz-Credential=releaseassetproduction%2F20250519%2Fus-east-1%2Fs3%2Faws4_request&X-Amz-Date=20250519T193931Z&X-Amz-Expires=300&X-Amz-Signature=8598b5c0ee780fc2463cd163a82aba16fd96b82d9d76de3669cd9c7d119e3032&X-Amz-SignedHeaders=host&response-content-disposition=attachment%3B%20filename%3Dpreload.js&response-content-type=application%2Foctet-stream"},"type":"http"},{"timestamp":1747683621.183,"category":"http","data":{"status_code":200,"url":"https://objects.githubusercontent.com/github-production-release-asset-2e65be/528464304/8c15ee34-4849-4cbc-9d6f-177e64804c97","http.method":"GET","http.query":"X-Amz-Algorithm=AWS4-HMAC-SHA256&X-Amz-Credential=releaseassetproduction%2F20250519%2Fus-east-1%2Fs3%2Faws4_request&X-Amz-Date=20250519T193837Z&X-Amz-Expires=300&X-Amz-Signature=ac17b37b353a28ea1711c2fd831f8ba1ab29898eb143bcce9999cae285ca2387&X-Amz-SignedHeaders=host&response-content-disposition=attachment%3B%20filename%3Drenderer.js.map&response-content-type=application%2Foctet-stream"},"type":"http"},{"timestamp":1747683621.224,"category":"http","data":{"status_code":200,"url":"https://objects.githubusercontent.com/github-production-release-asset-2e65be/528464304/f498968d-4865-4b18-93a0-bc3493e19b07","http.method":"GET","http.query":"X-Amz-Algorithm=AWS4-HMAC-SHA256&X-Amz-Credential=releaseassetproduction%2F20250519%2Fus-east-1%2Fs3%2Faws4_request&X-Amz-Date=20250519T193931Z&X-Amz-Expires=300&X-Amz-Signature=5433335702d6ae5efaedfd17c2bcdd210cd4597ea307857d8f64e00087df94cb&X-Amz-SignedHeaders=host&response-content-disposition=attachment%3B%20filename%3Dpreload.js.map&response-content-type=application%2Foctet-stream"},"type":"http"},{"timestamp":1747683621.317,"category":"http","data":{"status_code":200,"url":"https://objects.githubusercontent.com/github-production-release-asset-2e65be/528464304/4a1329fe-5353-4f92-9a91-e57761e7322b","http.method":"GET","http.query":"X-Amz-Algorithm=AWS4-HMAC-SHA256&X-Amz-Credential=releaseassetproduction%2F20250519%2Fus-east-1%2Fs3%2Faws4_request&X-Amz-Date=20250519T193837Z&X-Amz-Expires=300&X-Amz-Signature=112fc2547721a34975435817a2a6ae8d93e755abebc8d9edf485d27cd7545d27&X-Amz-SignedHeaders=host&response-content-disposition=attachment%3B%20filename%3Drenderer.css.map&response-content-type=application%2Foctet-stream"},"type":"http"},{"timestamp":1747683621.338,"category":"http","data":{"status_code":200,"url":"https://objects.githubusercontent.com/github-production-release-asset-2e65be/528464304/446b99c4-bfb6-4864-b2f2-833026b97699","http.method":"GET","http.query":"X-Amz-Algorithm=AWS4-HMAC-SHA256&X-Amz-Credential=releaseassetproduction%2F20250519%2Fus-east-1%2Fs3%2Faws4_request&X-Amz-Date=20250519T193931Z&X-Amz-Expires=300&X-Amz-Signature=8598b5c0ee780fc2463cd163a82aba16fd96b82d9d76de3669cd9c7d119e3032&X-Amz-SignedHeaders=host&response-content-disposition=attachment%3B%20filename%3Dpreload.js&response-content-type=application%2Foctet-stream"},"type":"http"},{"timestamp":1747683621.381,"category":"http","data":{"status_code":200,"url":"https://objects.githubusercontent.com/github-production-release-asset-2e65be/528464304/678c9cbe-2c69-4744-b6de-bb609409e8f3","http.method":"GET","http.query":"X-Amz-Algorithm=AWS4-HMAC-SHA256&X-Amz-Credential=releaseassetproduction%2F20250519%2Fus-east-1%2Fs3%2Faws4_request&X-Amz-Date=20250519T193837Z&X-Amz-Expires=300&X-Amz-Signature=d189648abd6402de6b0ae27e48ba96b44e6cf950f141a77e9cfbd0f59c78ef4a&X-Amz-SignedHeaders=host&response-content-disposition=attachment%3B%20filename%3Dpatcher.js&response-content-type=application%2Foctet-stream"},"type":"http"},{"timestamp":1747683709.15,"category":"electron","message":"window.focus","type":"ui","data":{"id":2,"url":"https://discord.com/channels/902483466308956241/910997069379026964"}},{"timestamp":1747683709.15,"category":"electron","message":"app.browser-window-focus","type":"ui"},{"timestamp":1747683709.175,"category":"console","data":{"arguments":["Subscribing to direct frames for streamId 10"],"logger":"console"},"level":"info","message":"Subscribing to direct frames for streamId 10"},{"timestamp":1747683710.024,"category":"electron","message":"window.blur","type":"ui","data":{"id":2,"url":"https://discord.com/channels/902483466308956241/910997069379026964"}},{"timestamp":1747683710.024,"category":"electron","message":"app.browser-window-blur","type":"ui"},{"timestamp":1747683710.068,"category":"console","data":{"arguments":["Unsubscribing from direct frames for streamId 10"],"logger":"console"},"level":"info","message":"Unsubscribing from direct frames for streamId 10"},{"timestamp":1747683710.35,"category":"electron","message":"window.focus","type":"ui","data":{"id":2,"url":"https://discord.com/channels/902483466308956241/910997069379026964"}},{"timestamp":1747683710.35,"category":"electron","message":"app.browser-window-focus","type":"ui"},{"timestamp":1747683710.375,"category":"console","data":{"arguments":["Subscribing to direct frames for streamId 10"],"logger":"console"},"level":"info","message":"Subscribing to direct frames for streamId 10"},{"timestamp":1747683711.688,"category":"ui.click","message":"g > g > g > g > path"},{"timestamp":1747683712.072,"category":"electron","message":"window.blur","type":"ui","data":{"id":2,"url":"https://discord.com/channels/902483466308956241/910997069379026964"}},{"timestamp":1747683712.072,"category":"electron","message":"app.browser-window-blur","type":"ui"},{"timestamp":1747683712.103,"category":"console","data":{"arguments":["Unsubscribing from direct frames for streamId 10"],"logger":"console"},"level":"info","message":"Unsubscribing from direct frames for streamId 10"},{"timestamp":1747684120.178,"category":"electron","message":"window.focus","type":"ui","data":{"id":2,"url":"https://discord.com/channels/902483466308956241/910997069379026964"}},{"timestamp":1747684120.178,"category":"electron","message":"app.browser-window-focus","type":"ui"},{"timestamp":1747684120.205,"category":"console","data":{"arguments":["Subscribing to direct frames for streamId 10"],"logger":"console"},"level":"info","message":"Subscribing to direct frames for streamId 10"},{"timestamp":1747684120.969,"category":"ui.click","message":"div.wrapper__1405b > div.buttonSection__1405b"},{"timestamp":1747684121.67,"category":"ui.click","message":"button.centerButton_f1ceac.colorable_f1ceac.primaryDark_f1ceac.attachedButton_f1ceac.button__201d5.lookBlank__201d5.colorBrand__201d5[aria-label=\"Mute\"][type=\"button\"]"},{"timestamp":1747684121.927,"category":"electron","message":"window.blur","type":"ui","data":{"id":2,"url":"https://discord.com/channels/902483466308956241/910997069379026964"}},{"timestamp":1747684121.927,"category":"electron","message":"app.browser-window-blur","type":"ui"},{"timestamp":1747684121.962,"category":"console","data":{"arguments":["Unsubscribing from direct frames for streamId 10"],"logger":"console"},"level":"info","message":"Unsubscribing from direct frames for streamId 10"}],"attachments":[],"contexts":{},"tags":{"nativeBuildNumber":"null"},"extra":{},"user":{"id":"498883797949874196","username":"thomeshu","email":"tomas.pecha@gmail.com"},"fingerprint":[],"eventProcessors":[],"propagationContext":{"traceId":"129de463fa244031ae4b542bc518cfd3","spanId":"9a46eab8ad6cd724"},"sdkProcessingMetadata":{}},"event":{"contexts":{"app":{"app_name":"discord","app_version":"0.0.94","app_start_time":"2025-05-19T11:40:13.562Z"},"os":{"kernel_version":"6.14.5-arch1-1","name":"Ubuntu Linux","version":"\"rolling\""},"browser":{"name":"Chrome"},"chrome":{"name":"Chrome","type":"runtime","version":"134.0.6998.179"},"device":{"arch":"x64","family":"Desktop"},"node":{"name":"Node","type":"runtime","version":"22.14.0"},"runtime":{"name":"Electron","version":"35.1.5"}},"environment":"stable","release":"0.0.94","user":{"ip_address":"{{auto}}"},"tags":{"event.origin":"electron","event.environment":"javascript","event.process":"browser","event_type":"javascript"}}}